{
  "bundle": {
    "active": true,
    "targets": ["dmg", "msi", "nsis", "appimage", "deb", "rpm"],
    "icon": ["icons/32x32.png", "icons/128x128.png", "icons/128x128@2x.png", "icons/icon.icns", "icons/icon.ico"],
    "resources": ["resources/bin/"],
    "externalBin": [],
    "copyright": "",
    "category": "DeveloperTool",
    "shortDescription": "",
    "longDescription": "",
    "macOS": {},
    "windows": {
      "certificateThumbprint": null,
      "digestAlgorithm": "sha256",
      "timestampUrl": "",
      "webviewInstallMode": {
        "type": "embedBootstrapper"
      },
      "nsis": {
        "installMode": "both",
        "installerIcon": "icons/icon.ico",
        "displayLanguageSelector": true,
        "minimumWebview2Version": "110.0.1531.0"
      }
    },
    "linux": {
      "deb": {},
      "rpm": {}
    }
  },
  "build": {
    "beforeBuildCommand": "pnpm generate",
    "frontendDist": "../dist",
    "beforeDevCommand": "pnpm dev",
    "devUrl": "http://localhost:3000"
  },
  "productName": "JumpServerClient",
  "version": "3.1.0",
  "identifier": "com.jumpserver.client",
  "plugins": {
    "deep-link": {
      "desktop": {
        "schemes": ["jms"]
      }
    }
  },
  "app": {
    "macOSPrivateApi": true,
    "windows": [
      {
        "label": "main",
        "title": "",
        "width": 1000,
        "height": 600,
        "minWidth": 800,
        "minHeight": 480,
        "resizable": true,
        "fullscreen": false,
        "transparent": true,
        "decorations": true,
        "titleBarStyle": "Overlay",
        "devtools": true,
        "trafficLightPosition": {
          "x": 10,
          "y": 18
        }
      }
    ],
    "security": {
      "csp": null,
      "dangerousDisableAssetCspModification": true
    },
    "withGlobalTauri": false
  }
}
